README.md
setup.py
pulumi_fortios/__init__.py
pulumi_fortios/_inputs.py
pulumi_fortios/_utilities.py
pulumi_fortios/alertemail_setting.py
pulumi_fortios/antivirus_exempt_list.py
pulumi_fortios/antivirus_heuristic.py
pulumi_fortios/antivirus_profile.py
pulumi_fortios/antivirus_quarantine.py
pulumi_fortios/antivirus_settings.py
pulumi_fortios/application_custom.py
pulumi_fortios/application_group.py
pulumi_fortios/application_list.py
pulumi_fortios/application_name.py
pulumi_fortios/application_rule_settings.py
pulumi_fortios/authentication_rule.py
pulumi_fortios/authentication_scheme.py
pulumi_fortios/authentication_setting.py
pulumi_fortios/automation_setting.py
pulumi_fortios/certificate_ca.py
pulumi_fortios/certificate_crl.py
pulumi_fortios/certificate_local.py
pulumi_fortios/certificate_remote.py
pulumi_fortios/cifs_domain_controller.py
pulumi_fortios/cifs_profile.py
pulumi_fortios/credential_store_domain_controller.py
pulumi_fortios/dlp_data_type.py
pulumi_fortios/dlp_dictionary.py
pulumi_fortios/dlp_filepattern.py
pulumi_fortios/dlp_fp_doc_source.py
pulumi_fortios/dlp_fp_sensitivity.py
pulumi_fortios/dlp_profile.py
pulumi_fortios/dlp_sensitivity.py
pulumi_fortios/dlp_sensor.py
pulumi_fortios/dlp_settings.py
pulumi_fortios/dnsfilter_domain_filter.py
pulumi_fortios/dnsfilter_profile.py
pulumi_fortios/dpdk_cpus.py
pulumi_fortios/dpdk_global.py
pulumi_fortios/emailfilter_block_allow_list.py
pulumi_fortios/emailfilter_bwl.py
pulumi_fortios/emailfilter_bword.py
pulumi_fortios/emailfilter_dnsbl.py
pulumi_fortios/emailfilter_fortishield.py
pulumi_fortios/emailfilter_iptrust.py
pulumi_fortios/emailfilter_mheader.py
pulumi_fortios/emailfilter_options.py
pulumi_fortios/emailfilter_profile.py
pulumi_fortios/endpoint_control_client.py
pulumi_fortios/endpoint_control_fctems.py
pulumi_fortios/endpoint_control_fctems_override.py
pulumi_fortios/endpoint_control_forticlient_ems.py
pulumi_fortios/endpoint_control_forticlient_registration_sync.py
pulumi_fortios.egg-info/PKG-INFO
pulumi_fortios.egg-info/SOURCES.txt
pulumi_fortios.egg-info/dependency_links.txt
pulumi_fortios.egg-info/not-zip-safe
pulumi_fortios.egg-info/requires.txt
pulumi_fortios.egg-info/top_level.txt
