Metadata-Version: 2.1
Name: pulumi-fortios
Version: 0.0.9
Summary: A Pulumi package for creating and managing fortios cloud resources.
Home-page: https://www.pulumi.com
License: Apache-2.0
Project-URL: Repository, https://github.com/pulumi/pulumi-fortios
Keywords: pulumi fortios category/cloud
Platform: UNKNOWN
Requires-Python: >=3.7
